ptouch/__init__.py
ptouch/__main__.py
ptouch/config.py
ptouch/connection.py
ptouch/label.py
ptouch/printer.py
ptouch/printers.py
ptouch/tape.py
ptouch-1.0.0.dist-info/licenses/LICENSE
ptouch-1.0.0.dist-info/METADATA
ptouch-1.0.0.dist-info/WHEEL
ptouch-1.0.0.dist-info/entry_points.txt
ptouch-1.0.0.dist-info/top_level.txt
ptouch-1.0.0.dist-info/RECORD
