Metadata-Version: 2.4
Name: ptouch
Version: 1.0.0
Summary: Python library for Brother P-touch label printers
Author-email: Nicolai Buchwitz <nb@tipi-net.de>
Maintainer-email: Nicolai Buchwitz <nb@tipi-net.de>
Keywords: brother,p-touch,label,printer,raster
Classifier: Development Status :: 4 - Beta
Classifier: Intended Audience :: Developers
Classifier: License :: OSI Approved :: GNU Lesser General Public License v2 or later (LGPLv2+)
Classifier: Operating System :: OS Independent
Classifier: Programming Language :: Python :: 3
Classifier: Programming Language :: Python :: 3.11
Classifier: Programming Language :: Python :: 3.12
Classifier: Topic :: Printing
Requires-Python: >=3.11
License-File: LICENSE
Requires-Dist: Pillow
Requires-Dist: packbits
Provides-Extra: usb
Requires-Dist: pyusb; extra == "usb"
Provides-Extra: dev
Requires-Dist: ruff; extra == "dev"
Requires-Dist: mypy; extra == "dev"
Provides-Extra: test
Requires-Dist: pytest; extra == "test"
Requires-Dist: pytest-cov; extra == "test"
Requires-Dist: pyusb; extra == "test"
Dynamic: license-file
